ZabbixTuner.py
setup.py
conf/__init__.py
conf/zabbix.py
zabbix_tuner.egg-info/PKG-INFO
zabbix_tuner.egg-info/SOURCES.txt
zabbix_tuner.egg-info/dependency_links.txt
zabbix_tuner.egg-info/not-zip-safe
zabbix_tuner.egg-info/requires.txt
zabbix_tuner.egg-info/top_level.txt