Metadata-Version: 1.1
Name: zabbix-tuner
Version: 0.2
Summary: Zabbix Tuner
Home-page: https://github.com/janssenlima/ZabbixTuner
Author: Janssen dos Reis Lima
Author-email: janssenreislima@gmail.com
License: GNU LGPL 2.1
Keywords: zabbix api tuner tuning
Platform: any
Classifier: Programming Language :: Python
Classifier: Programming Language :: Python :: 2
Classifier: Development Status :: 2 - Pre-Alpha
